palimpsest/.character_reader.py.swp
palimpsest/__about__.py
palimpsest/__init__.py
palimpsest/character_reader.py
palimpsest-0.0.2.dist-info/METADATA
palimpsest-0.0.2.dist-info/WHEEL
palimpsest-0.0.2.dist-info/licenses/LICENSE.txt
palimpsest-0.0.2.dist-info/RECORD
